monitorium/__init__.py
monitorium-0.0.1.dist-info/LICENCE
monitorium-0.0.1.dist-info/METADATA
monitorium-0.0.1.dist-info/WHEEL
monitorium-0.0.1.dist-info/RECORD
